README
setup.py
pyurfa/__init__.py
pyurfa/client.py
pyurfa/clientadmin.py
pyurfa/packet.py
pyurfa.egg-info/PKG-INFO
pyurfa.egg-info/SOURCES.txt
pyurfa.egg-info/dependency_links.txt
pyurfa.egg-info/top_level.txt