Metadata-Version: 1.1
Name: pyurfa
Version: 0.0.1
Summary: Python api for UTM5 Billing
Home-page: http://bitbucket.org/chubi/pyurfa
Author: Ilia Gavrilin
Author-email: gavrilin.ilia@gmail.com
License: BSD
Keywords: netup utm5 api
Platform: UNKNOWN
Classifier: Operating System :: OS Independent
Classifier: Programming Language :: Python
